nat/meta/pypi.md
nat/plugins/openpipe/__init__.py
nat/plugins/openpipe/config.py
nat/plugins/openpipe/register.py
nat/plugins/openpipe/trainer.py
nat/plugins/openpipe/trainer_adapter.py
nat/plugins/openpipe/trajectory_builder.py
nvidia_nat_openpipe_art-1.5.0a20260130.dist-info/licenses/LICENSE-3rd-party.txt
nvidia_nat_openpipe_art-1.5.0a20260130.dist-info/licenses/LICENSE.md
nvidia_nat_openpipe_art-1.5.0a20260130.dist-info/METADATA
nvidia_nat_openpipe_art-1.5.0a20260130.dist-info/WHEEL
nvidia_nat_openpipe_art-1.5.0a20260130.dist-info/entry_points.txt
nvidia_nat_openpipe_art-1.5.0a20260130.dist-info/top_level.txt
nvidia_nat_openpipe_art-1.5.0a20260130.dist-info/RECORD
