Metadata-Version: 2.4
Name: nvidia-nat-openpipe-art
Version: 1.5.0a20260130
Summary: Subpackage for OpenPipe ART integration in NeMo Agent toolkit
Author: NVIDIA Corporation
Maintainer: NVIDIA Corporation
License: Apache-2.0
Project-URL: documentation, https://docs.nvidia.com/nemo/agent-toolkit/latest/
Project-URL: source, https://github.com/NVIDIA/NeMo-Agent-Toolkit
Keywords: ai,finetuning
Classifier: Programming Language :: Python
Classifier: Programming Language :: Python :: 3.11
Classifier: Programming Language :: Python :: 3.12
Classifier: Programming Language :: Python :: 3.13
Requires-Python: <3.14,>=3.11
License-File: LICENSE-3rd-party.txt
License-File: LICENSE.md
Requires-Dist: nvidia-nat[litellm]==v1.5.0a20260130
Requires-Dist: matplotlib~=3.9
Requires-Dist: openpipe-art==0.5.4
Dynamic: license-file
